LICENSE
MANIFEST.in
README.rst
setup.cfg
setup.py
web2sms/__init__.py
web2sms/api.py
web2sms/test.py
web2sms.egg-info/PKG-INFO
web2sms.egg-info/SOURCES.txt
web2sms.egg-info/dependency_links.txt
web2sms.egg-info/entry_points.txt
web2sms.egg-info/not-zip-safe
web2sms.egg-info/requires.txt
web2sms.egg-info/top_level.txt