Metadata-Version: 1.0
Name: web2sms
Version: 0.2dev
Summary: A python client for Cosmote web2sms service.
Home-page: http://www.bitbucket.org/vinilios
Author: Kostas Papadimitriou
Author-email: vinilios@gmail.com
License: GNU LGPL
Keywords: sms api cosmote greece mobile client
Platform: UNKNOWN
Classifier: Development Status :: 4 - Beta
Classifier: Topic :: Communications :: Telephony
